setup.py
forecast12hrs/__init__.py
forecast12hrs/forecast12hrs.py
forecast12hrs.egg-info/PKG-INFO
forecast12hrs.egg-info/SOURCES.txt
forecast12hrs.egg-info/dependency_links.txt
forecast12hrs.egg-info/requires.txt
forecast12hrs.egg-info/top_level.txt