Metadata-Version: 2.1
Name: forecast12hrs
Version: 1.0.0
Summary: Weather forecast data
Home-page: UNKNOWN
Author: Ray
License: MIT
Platform: UNKNOWN
Classifier: Development Status :: 3 - Alpha
Classifier: Intended Audience :: Developers
